pppSupplPy/__init__.py
pppSupplPy-0.0.2.dist-info/METADATA
pppSupplPy-0.0.2.dist-info/RECORD
pppSupplPy-0.0.2.dist-info/WHEEL
pppSupplPy-0.0.2.dist-info/top_level.txt
