Metadata-Version: 2.1
Name: pppSupplPy
Version: 0.0.2
Summary: A supplement Python package for PrePhyloPro
Home-page: http://yulongniu.bionutshell.org/
Author: YulongNiu
Author-email: yulong.niu@hotmail.com
License: UNKNOWN
Project-URL: Web application, http://bioinfor.scu.edu.cn/phyloprofile/
Project-URL: Source, https://github.com/YulongNiu/PhyloProfileWeb
Platform: UNKNOWN
